AUTHORS
LICENSE.txt
MANIFEST.in
README.rst
requirements-dev.txt
requirements.txt
setup.cfg
setup.py
artwork/logo.svg
influxable/__init__.py
influxable/api.py
influxable/app.py
influxable/attributes.py
influxable/command_line.py
influxable/connection.py
influxable/decorators.py
influxable/exceptions.py
influxable/measurement.py
influxable/request.py
influxable/response.py
influxable/serializers.py
influxable/settings.py
influxable.egg-info/PKG-INFO
influxable.egg-info/SOURCES.txt
influxable.egg-info/dependency_links.txt
influxable.egg-info/entry_points.txt
influxable.egg-info/requires.txt
influxable.egg-info/top_level.txt
influxable/commands/__init__.py
influxable/commands/auto_generate.py
influxable/commands/populate.py
influxable/db/__init__.py
influxable/db/admin.py
influxable/db/criteria.py
influxable/db/query.py
influxable/db/function/__init__.py
influxable/db/function/aggregations.py
influxable/db/function/selectors.py
influxable/db/function/transformations.py
influxable/helpers/__init__.py
influxable/helpers/decorators.py
influxable/helpers/utils.py
tests/__init__.py
tests/test_app.py
tests/test_attributes.py
tests/test_connection.py
tests/test_db_admin.py
tests/test_db_query.py
tests/test_influx_api.py
tests/test_measurement.py
tests/test_serializers.py
tests/test_settings.py