Metadata-Version: 2.1
Name: influxable
Version: 1.4.1
Summary: A lightweight python ORM / ODM for InfluxDB
Home-page: https://github.com/Javidjms/influxable
Download-URL: https://github.com/Javidjms/influxable/archive/1.4.1.zip
Author: Javid Mougamadou
Author-email: javidjms0@gmail.com
License: MIT
Project-URL: Source, https://github.com/Javidjms/influxable
Keywords: python,influxdb,odm,orm,driver,client
Classifier: Development Status :: 3 - Alpha
Classifier: Intended Audience :: Developers
Classifier: Topic :: Software Development :: Build Tools
Classifier: License :: OSI Approved :: MIT License
Classifier: Programming Language :: Python :: 3
Classifier: Programming Language :: Python :: 3.4
Classifier: Programming Language :: Python :: 3.5
Classifier: Programming Language :: Python :: 3.6
Requires-Python: >=3.4
License-File: LICENSE.txt
License-File: AUTHORS
